setup.py
distributions/Binomialdistribution.py
distributions/Gaussiandistribution.py
distributions/Generaldistribution.py
distributions/__init__.py
jocombust_distributions.egg-info/PKG-INFO
jocombust_distributions.egg-info/SOURCES.txt
jocombust_distributions.egg-info/dependency_links.txt
jocombust_distributions.egg-info/not-zip-safe
jocombust_distributions.egg-info/top_level.txt